still_alive/__init__.py
still_alive/mouse_mover.py
still_alive-1.1.1.dist-info/LICENSE
still_alive-1.1.1.dist-info/METADATA
still_alive-1.1.1.dist-info/WHEEL
still_alive-1.1.1.dist-info/entry_points.txt
still_alive-1.1.1.dist-info/top_level.txt
still_alive-1.1.1.dist-info/RECORD
