Metadata-Version: 2.1
Name: still-alive
Version: 1.1.1
Summary: A Command-line tool that moves the mouse slightly at regular intervals
Home-page: https://github.com/pythonpioneer/Still-Alive
Author: pythonpioneer
Author-email: kumarhritiksinha@gmail.com
License: UNKNOWN
Platform: UNKNOWN
Classifier: Programming Language :: Python :: 3
Classifier: Operating System :: OS Independent
Classifier: License :: OSI Approved :: MIT License
Classifier: Environment :: Console
Requires-Python: >=3.6
License-File: LICENSE
Requires-Dist: pyautogui
